{
    "products": [
        {
            "precision": 2,
            "price": "R$ 45.33",
            "name": "Arroz Doce",
            "Due date": "31/03/2039 02:08:03",
            "_id": "d00e694542b7f491"
        },
        {
            "precision": 3,
            "price": "R$ 62.706",
            "name": "Sorvete",
            "Due date": "23/11/2027 19:27:49",
            "_id": "15db460fb0e6354f"
        },
        {
            "precision": 4,
            "price": "R$ 79.0277",
            "name": "Feij\u00c3\u00a3o",
            "Due date": "06/11/2020 08:34:37",
            "_id": "9e4dc7839fd899ab"
        },
        {
            "precision": 2,
            "price": "R$ 53.4",
            "name": "Batata",
            "Due date": "04/10/2021 07:26:26",
            "_id": "2a82799da25db26e"
        }
    ]
}